{
  "success": true,
  "data": [
    {
      "id": 1,
      "img": "https://jb-ph-cdn.tillster.com/menu-images/prod/c50a90f9-9e3f-47b0-82ca-309c5d856369.png",
      "description": "8 - pc. Chickenjoy Bucket w/ Jolly Spaghetti Family Pan",
      "price": 760.00
    },
    {
      "id": 2,
      "img": "https://jb-ph-cdn.tillster.com/menu-images/prod/9c3aec9f-9cf5-40f2-8ffb-98e4035f4007.png",
      "description": "6 - pc. Chickenjoy with Palabok Family Pan",
      "price": 880.00
    },
    {
      "id": 3,
      "img": "https://jb-ph-cdn.tillster.com/menu-images/prod/9c3aec9f-9cf5-40f2-8ffb-98e4035f4007.png",
      "description": "8 - pc. Chickenjoy with Palabok Family Pan",
      "price": 980.00
    },
    {
      "id": 4,
      "img": "https://jb-ph-cdn.tillster.com/menu-images/prod/38d94f98-3b41-4a15-ba1c-d772fb231c7d.png",
      "description": "6 - pc. Chickenjoy Solo",
      "price": 435.00
    },
    {
      "id": 5,
      "img": "https://jb-ph-cdn.tillster.com/menu-images/prod/38d94f98-3b41-4a15-ba1c-d772fb231c7d.png",
      "description": "8 - pc. Chickenjoy Solo",
      "price": 535.00
    },
    {
      "id": 6,
      "img": "https://jb-ph-cdn.tillster.com/menu-images/prod/e39c15e2-e026-4676-be4d-f645c9c1887d.png",
      "description": "4 - pc. Chickenjoy Family Box Solo",
      "price": 325.00
    },
    {
      "id": 7,
      "img": "https://jb-ph-cdn.tillster.com/menu-images/prod/d9253c52-eb96-4e78-be5a-4f71eea7eded.png",
      "description": "Chickenjoy Bucket Family Meals",
      "price": 758.00
    },
    {
      "id": 8,
      "img": "https://jb-ph-cdn.tillster.com/menu-images/prod/97c65d20-e66c-4b30-9a8c-5fcfa61d375b.png",
      "description": "Jolly Spaghetti & Palabok Family Pan",
      "price": 235.00
    },
    {
      "id": 9,
      "img": "https://jb-ph-cdn.tillster.com/menu-images/prod/a8d20051-ceb5-4558-a715-9f710413e360.png",
      "description": "Burger Bundle",
      "price": 366.00
    },
    {
      "id": 10,
      "img": "https://jb-ph-cdn.tillster.com/menu-images/prod/4c6d9484-4df8-4fdd-bd5a-b5ecb9547bf2.png",
      "description": "Yumburger Family Savers",
      "price": 265.00
    },
    {
      "id": 11,
      "img": "https://jb-ph-cdn.tillster.com/menu-images/prod/381554be-a9c4-4bc5-8da9-ba19b0588ce8.png",
      "description": "2 1-pc. Burger Steak w/ Drink and 2 Choco Mallow Pie",
      "price": 250.00
    },
    {
      "id": 12,
      "img": "https://jb-ph-cdn.tillster.com/menu-images/prod/f794381c-bc66-4c18-903c-e944969a46b0.png",
      "description": "Burger Steak Family Savers",
      "price": 297.00
    },
    {
      "id": 13,
      "img": "https://jb-ph-cdn.tillster.com/menu-images/prod/6f1cbe74-0cfb-4431-976a-2584adf1e8da.png",
      "description": "6-pc. Burger Steak Family Pan",
      "price": 348.00
    },
    {
      "id": 14,
      "img": "https://jb-ph-cdn.tillster.com/menu-images/prod/6241ec46-1620-42b1-ba8e-5597377b4741.png",
      "description": "8-pc. Burger Steak Family Pan",
      "price": 450.00
    },
    {
      "id": 15,
      "img": "https://jb-ph-cdn.tillster.com/menu-images/prod/94703812-5034-443c-94aa-60ca3f22abe1.png",
      "description": "6-pc. Burger Steak w/ Jolly Spaghetti Family Pan",
      "price": 550.00
    },
    {
      "id": 16,
      "img": "https://jb-ph-cdn.tillster.com/menu-images/prod/69fb5f8f-cccd-435f-8521-bddcd1afd7f1.png",
      "description": "8-pc. Burger Steak w/ Jolly Spaghetti Family Pan",
      "price": 630.00
    },
    {
      "id": 17,
      "img": "https://jb-ph-cdn.tillster.com/menu-images/prod/81a52ea8-05ca-4373-9c33-8fb93f0b55f7.png",
      "description": "6-pc. Burger Steak w/ Palabok Family Pan",
      "price": 801.00
    },
    {
      "id": 18,
      "img": "https://jb-ph-cdn.tillster.com/menu-images/prod/15a9fa25-c1b2-4a50-8610-4b78a7f938f7.png",
      "description": "8-pc. Burger Steak w/ Palabok Family Pan",
      "price": 896.00
    },
    {
      "id": 19,
      "img": "https://jb-ph-cdn.tillster.com/menu-images/prod/c18ce51a-da21-4f17-83f3-5ce4fac7214d.png",
      "description": "Jolly Crispy Fries Bucket",
      "price": 158.00
    },
    {
      "id": 20,
      "img": "https://jb-ph-cdn.tillster.com/menu-images/prod/6ca796b4-b869-4131-b2e7-05d64962b4a8.png",
      "description": "Sweet 6 Pies To-Go",
      "price": 265.00
    },
    {
      "id": 21,
      "img": "https://jb-ph-cdn.tillster.com/menu-images/prod/950237c7-4a85-4cce-a138-36db6a2a8658.png",
      "description": "Joy At Home Birthday Set",
      "price": 80.00
    }
  ]
}
